lf_asv_formatter/__init__.py
lf_asv_formatter/__main__.py
lf_asv_formatter/_version.py
lf_asv_formatter/asv_formatter.py
lf_asv_formatter/simple_formatter.py
lf_asv_formatter/tabulate_formatter.py
lf_asv_formatter-0.0.3.dist-info/LICENSE
lf_asv_formatter-0.0.3.dist-info/METADATA
lf_asv_formatter-0.0.3.dist-info/WHEEL
lf_asv_formatter-0.0.3.dist-info/top_level.txt
lf_asv_formatter-0.0.3.dist-info/RECORD
